Workbook

Sheet Léame
A1: Proyección de recursos · CESSUM
A2: Preparada el 23 de septiembre de 2026 para Vicerrectoría y Administración y Finanzas.
A4: CÓMO SE USA
A5: 1. En «Supuestos», cambie cualquier celda azul con fondo amarillo. Todo se recalcula.
A6: 2. En «Supuestos!B4» elija el escenario que se proyecta: 1 Pesimista, 2 Base, 3 Optimista.
A7: 3. Capture el saldo inicial real de las DOS cuentas al 1 de septiembre de 2026 (Supuestos, último renglón).
A8: 4. En «Proyección», capture los gastos extraordinarios de cada mes (graduación, aguinaldos, impuestos).
A9: 5. «Comparativo» muestra los tres escenarios a la vez y comprueba que cuadren con la Proyección.
A11: DE DÓNDE SALEN LOS NÚMEROS
A12: · Agosto 2026, cuenta BBVA 0120887013, leído y cuadrado al centavo: abonos $640,726.26 y cargos $385,912.83.
A13: · Unos 400 alumnos activos en el ciclo 2026-2027 × colegiaturas vigentes (hoja PlanPagos del Guardián) ≈ $640,000 al mes.
A14: · Precios: convocatoria de posgrado 26-4/27-1 y hoja PlanPagos. Titulación: flyers vigentes.
... A23: Cuando la app cargue los 37 meses de las dos cuentas, la pestaña Proyección de Finanzas da el pronóstico con datos reales y banda de confianza del 95 %.

Sheet Supuestos
A1: Proyección de recursos CESSUM · Supuestos
A2: Azul con fondo amarillo = dato editable. Cambie cualquiera y todo el libro se recalcula.
A4: Escenario activo (1 = Pesimista, 2 = Base, 3 = Optimista) | B4: 2 | C4: =INDEX(C6:E6,1,$B$4) -> Base
A6: Supuesto | B6: Unidad | C6: Pesimista | D6: Base | E6: Optimista | F6: En uso
A7: Colegiaturas mensuales de los alumnos actuales | B7: $ al mes | C7: 560000 | D7: 600000 | E7: 630000 | F7: =INDEX(C7:E7,1,$B$4) -> 600000
A8: Alumnos de Licenciatura 26-3 | B8: alumnos | C8: 8 | D8: 8 | E8: 8 | F8: =INDEX(C8:E8,1,$B$4) -> 8
A9: Colegiatura Licenciatura | B9: $ al mes | C9: 1850 | D9: 1850 | E9: 1850 | F9: =INDEX(C9:E9,1,$B$4) -> 1850
A10: Inscritos Maestría en Educación 26-4 (inicia 5-oct-2026) | B10: alumnos | C10: 30 | D10: 45 | E10: 60 | F10: =INDEX(C10:E10,1,$B$4) -> 45
A11: Colegiatura Maestría en Educación 26-4 | B11: $ al mes | C11: 2850 | D11: 2850 | E11: 2850 | F11: =INDEX(C11:E11,1,$B$4) -> 2850
A12: Inscripción | B12: $ única | C12: 450 | D12: 450 | E12: 450 | F12: =INDEX(C12:E12,1,$B$4) -> 450
A13: Reinscripción | B13: $ por periodo | C13: 350 | D13: 350 | E13: 350 | F13: =INDEX(C13:E13,1,$B$4) -> 350
A14: Egresados que dejan de pagar desde enero 2027 | B14: alumnos | C14: 135 | D14: 110 | E14: 90 | F14: =INDEX(C14:E14,1,$B$4) -> 110
A15: Cuota mensual promedio que dejan de pagar | B15: $ al mes | C15: 1900 | D15: 1800 | E15: 1700 | F15: =INDEX(C15:E15,1,$B$4) -> 1800
A16: Inscritos posgrados 27-1 (inicia 11-ene-2027) | B16: alumnos | C16: 80 | D16: 110 | E16: 140 | F16: =INDEX(C16:E16,1,$B$4) -> 110
A17: Colegiatura promedio 27-1 | B17: $ al mes | C17: 1450 | D17: 1450 | E17: 1450 | F17: =INDEX(C17:E17,1,$B$4) -> 1450
A18: Alumnos que continúan y se reinscriben (enero y julio) | B18: alumnos | C18: 150 | D18: 150 | E18: 150 | F18: =INDEX(C18:E18,1,$B$4) -> 150
... A24: Saldo inicial al 1 de septiembre de 2026 (las dos cuentas) | B24: $ | C24: 0 | D24: 0 | E24: 0 | F24: =INDEX(C24:E24,1,$B$4) -> 0

Sheet Proyección
A1: Proyección mensual · septiembre 2026 a agosto 2027
A2: =CONCATENATE("Escenario en uso: ",Supuestos!C4," (cámbielo en Supuestos!B4)") -> Escenario en uso: Base (cámbielo en Supuestos!B4)
A4: Concepto | B4: Nota | C4: sep 26 | D4: oct 26 | E4: nov 26 | F4: dic 26 | G4: ene 27 | H4: feb 27 | I4: mar 27 | J4: abr 27 | K4: may 27 | L4: jun 27 | M4: jul 27 | N4: ago 27 | O4: Total 12 meses
A5: Mes número | C5: 1 | D5: 2 | E5: 3 | F5: 4 | G5: 5 | H5: 6 | I5: 7 | J5: 8 | K5: 9 | L5: 10 | M5: 11 | N5: 12
A6: INGRESOS
A7: Colegiaturas de alumnos actuales | B7: Desde septiembre | C7: =Supuestos!$F$7 -> 600000 | D7: =Supuestos!$F$7 -> 600000 | E7: =Supuestos!$F$7 -> 600000 | F7: =Supuestos!$F$7 -> 600000 | G7: =Supuestos!$F$7 -> 600000 | H7: =Supuestos!$F$7 -> 600000 | I7: =Supuestos!$F$7 -> 600000 | J7: =Supuestos!$F$7 -> 600000 | ... N7: =Supuestos!$F$7 -> 600000 | O7: =SUM(C7:N7) -> 7200000
A8: Licenciatura 26-3 | B8: Alumnos × colegiatura | C8: =Supuestos!$F$8*Supuestos!$F$9 -> 14800 | D8: =Supuestos!$F$8*Supuestos!$F$9 -> 14800 | E8: =Supuestos!$F$8*Supuestos!$F$9 -> 14800 | F8: =Supuestos!$F$8*Supuestos!$F$9 -> 14800 | G8: =Supuestos!$F$8*Supuestos!$F$9 -> 14800 | H8: =Supuestos!$F$8*Supuestos!$F$9 -> 14800 | I8: =Supuestos!$F$8*Supuestos!$F$9 -> 14800 | J8: =Supuestos!$F$8*Supuestos!$F$9 -> 14800 | ... N8: =Supuestos!$F$8*Supuestos!$F$9 -> 14800 | O8: =SUM(C8:N8) -> 177600
A9: Inscripción Maestría en Educación 26-4 | B9: Mitad en sep, mitad en oct | C9: =IF(OR(C$5=1,C$5=2),Supuestos!$F$10*Supuestos!$F$12/2,0) -> 10125 | D9: =IF(OR(D$5=1,D$5=2),Supuestos!$F$10*Supuestos!$F$12/2,0) -> 10125 | E9: =IF(OR(E$5=1,E$5=2),Supuestos!$F$10*Supuestos!$F$12/2,0) -> 0 | F9: =IF(OR(F$5=1,F$5=2),Supuestos!$F$10*Supuestos!$F$12/2,0) -> 0 | G9: =IF(OR(G$5=1,G$5=2),Supuestos!$F$10*Supuestos!$F$12/2,0) -> 0 | H9: =IF(OR(H$5=1,H$5=2),Supuestos!$F$10*Supuestos!$F$12/2,0) -> 0 | I9: =IF(OR(I$5=1,I$5=2),Supuestos!$F$10*Supuestos!$F$12/2,0) -> 0 | J9: =IF(OR(J$5=1,J$5=2),Supuestos!$F$10*Supuestos!$F$12/2,0) -> 0 | ... N9: =IF(OR(N$5=1,N$5=2),Supuestos!$F$10*Supuestos!$F$12/2,0) -> 0 | O9: =SUM(C9:N9) -> 20250
A10: Colegiaturas Maestría en Educación 26-4 | B10: Desde octubre | C10: =IF(C$5>=2,Supuestos!$F$10*Supuestos!$F$11,0) -> 0 | D10: =IF(D$5>=2,Supuestos!$F$10*Supuestos!$F$11,0) -> 128250 | E10: =IF(E$5>=2,Supuestos!$F$10*Supuestos!$F$11,0) -> 128250 | F10: =IF(F$5>=2,Supuestos!$F$10*Supuestos!$F$11,0) -> 128250 | G10: =IF(G$5>=2,Supuestos!$F$10*Supuestos!$F$11,0) -> 128250 | H10: =IF(H$5>=2,Supuestos!$F$10*Supuestos!$F$11,0) -> 128250 | I10: =IF(I$5>=2,Supuestos!$F$10*Supuestos!$F$11,0) -> 128250 | J10: =IF(J$5>=2,Supuestos!$F$10*Supuestos!$F$11,0) -> 128250 | ... N10: =IF(N$5>=2,Supuestos!$F$10*Supuestos!$F$11,0) -> 128250 | O10: =SUM(C10:N10) -> 1410750
A11: Reinscripción 26-4 (trimestral) | B11: Enero, abril y julio | C11: =IF(OR(C$5=5,C$5=8,C$5=11),Supuestos!$F$10*Supuestos!$F$13,0) -> 0 | D11: =IF(OR(D$5=5,D$5=8,D$5=11),Supuestos!$F$10*Supuestos!$F$13,0) -> 0 | E11: =IF(OR(E$5=5,E$5=8,E$5=11),Supuestos!$F$10*Supuestos!$F$13,0) -> 0 | F11: =IF(OR(F$5=5,F$5=8,F$5=11),Supuestos!$F$10*Supuestos!$F$13,0) -> 0 | G11: =IF(OR(G$5=5,G$5=8,G$5=11),Supuestos!$F$10*Supuestos!$F$13,0) -> 15750 | H11: =IF(OR(H$5=5,H$5=8,H$5=11),Supuestos!$F$10*Supuestos!$F$13,0) -> 0 | I11: =IF(OR(I$5=5,I$5=8,I$5=11),Supuestos!$F$10*Supuestos!$F$13,0) -> 0 | J11: =IF(OR(J$5=5,J$5=8,J$5=11),Supuestos!$F$10*Supuestos!$F$13,0) -> 15750 | ... N11: =IF(OR(N$5=5,N$5=8,N$5=11),Supuestos!$F$10*Supuestos!$F$13,0) -> 0 | O11: =SUM(C11:N11) -> 47250
A12: Egresados que dejan de pagar | B12: Desde enero (resta) | C12: =IF(C$5>=5,-Supuestos!$F$14*Supuestos!$F$15,0) -> 0 | D12: =IF(D$5>=5,-Supuestos!$F$14*Supuestos!$F$15,0) -> 0 | E12: =IF(E$5>=5,-Supuestos!$F$14*Supuestos!$F$15,0) -> 0 | F12: =IF(F$5>=5,-Supuestos!$F$14*Supuestos!$F$15,0) -> 0 | G12: =IF(G$5>=5,-Supuestos!$F$14*Supuestos!$F$15,0) -> -198000 | H12: =IF(H$5>=5,-Supuestos!$F$14*Supuestos!$F$15,0) -> -198000 | I12: =IF(I$5>=5,-Supuestos!$F$14*Supuestos!$F$15,0) -> -198000 | J12: =IF(J$5>=5,-Supuestos!$F$14*Supuestos!$F$15,0) -> -198000 | ... N12: =IF(N$5>=5,-Supuestos!$F$14*Supuestos!$F$15,0) -> -198000 | O12: =SUM(C12:N12) -> -1584000
A13: Inscripción posgrados 27-1 | B13: Mitad en dic, mitad en ene | C13: =IF(OR(C$5=4,C$5=5),Supuestos!$F$16*Supuestos!$F$12/2,0) -> 0 | D13: =IF(OR(D$5=4,D$5=5),Supuestos!$F$16*Supuestos!$F$12/2,0) -> 0 | E13: =IF(OR(E$5=4,E$5=5),Supuestos!$F$16*Supuestos!$F$12/2,0) -> 0 | F13: =IF(OR(F$5=4,F$5=5),Supuestos!$F$16*Supuestos!$F$12/2,0) -> 24750 | G13: =IF(OR(G$5=4,G$5=5),Supuestos!$F$16*Supuestos!$F$12/2,0) -> 24750 | H13: =IF(OR(H$5=4,H$5=5),Supuestos!$F$16*Supuestos!$F$12/2,0) -> 0 | I13: =IF(OR(I$5=4,I$5=5),Supuestos!$F$16*Supuestos!$F$12/2,0) -> 0 | J13: =IF(OR(J$5=4,J$5=5),Supuestos!$F$16*Supuestos!$F$12/2,0) -> 0 | ... N13: =IF(OR(N$5=4,N$5=5),Supuestos!$F$16*Supuestos!$F$12/2,0) -> 0 | O13: =SUM(C13:N13) -> 49500
A14: Colegiaturas posgrados 27-1 | B14: Desde enero | C14: =IF(C$5>=5,Supuestos!$F$16*Supuestos!$F$17,0) -> 0 | D14: =IF(D$5>=5,Supuestos!$F$16*Supuestos!$F$17,0) -> 0 | E14: =IF(E$5>=5,Supuestos!$F$16*Supuestos!$F$17,0) -> 0 | F14: =IF(F$5>=5,Supuestos!$F$16*Supuestos!$F$17,0) -> 0 | G14: =IF(G$5>=5,Supuestos!$F$16*Supuestos!$F$17,0) -> 159500 | H14: =IF(H$5>=5,Supuestos!$F$16*Supuestos!$F$17,0) -> 159500 | I14: =IF(I$5>=5,Supuestos!$F$16*Supuestos!$F$17,0) -> 159500 | J14: =IF(J$5>=5,Supuestos!$F$16*Supuestos!$F$17,0) -> 159500 | ... N14: =IF(N$5>=5,Supuestos!$F$16*Supuestos!$F$17,0) -> 159500 | O14: =SUM(C14:N14) -> 1276000
A15: Reinscripción 27-1 (semestral) | B15: Julio | C15: =IF(C$5=11,Supuestos!$F$16*Supuestos!$F$13,0) -> 0 | D15: =IF(D$5=11,Supuestos!$F$16*Supuestos!$F$13,0) -> 0 | E15: =IF(E$5=11,Supuestos!$F$16*Supuestos!$F$13,0) -> 0 | F15: =IF(F$5=11,Supuestos!$F$16*Supuestos!$F$13,0) -> 0 | G15: =IF(G$5=11,Supuestos!$F$16*Supuestos!$F$13,0) -> 0 | H15: =IF(H$5=11,Supuestos!$F$16*Supuestos!$F$13,0) -> 0 | I15: =IF(I$5=11,Supuestos!$F$16*Supuestos!$F$13,0) -> 0 | J15: =IF(J$5=11,Supuestos!$F$16*Supuestos!$F$13,0) -> 0 | ... N15: =IF(N$5=11,Supuestos!$F$16*Supuestos!$F$13,0) -> 0 | O15: =SUM(C15:N15) -> 38500
A16: Reinscripción de alumnos que continúan | B16: Enero y julio | C16: =IF(OR(C$5=5,C$5=11),Supuestos!$F$18*Supuestos!$F$13,0) -> 0 | D16: =IF(OR(D$5=5,D$5=11),Supuestos!$F$18*Supuestos!$F$13,0) -> 0 | E16: =IF(OR(E$5=5,E$5=11),Supuestos!$F$18*Supuestos!$F$13,0) -> 0 | F16: =IF(OR(F$5=5,F$5=11),Supuestos!$F$18*Supuestos!$F$13,0) -> 0 | G16: =IF(OR(G$5=5,G$5=11),Supuestos!$F$18*Supuestos!$F$13,0) -> 52500 | H16: =IF(OR(H$5=5,H$5=11),Supuestos!$F$18*Supuestos!$F$13,0) -> 0 | I16: =IF(OR(I$5=5,I$5=11),Supuestos!$F$18*Supuestos!$F$13,0) -> 0 | J16: =IF(OR(J$5=5,J$5=11),Supuestos!$F$18*Supuestos!$F$13,0) -> 0 | ... N16: =IF(OR(N$5=5,N$5=11),Supuestos!$F$18*Supuestos!$F$13,0) -> 0 | O16: =SUM(C16:N16) -> 105000
A17: Titulación de egresados | B17: Repartida desde enero | C17: =IF(AND(C$5>=5,C$5<5+Supuestos!$F$22),Supuestos!$F$19*Supuestos!$F$20*Supuestos!$F$21/Supuestos!$F$22,0) -> 0 | D17: =IF(AND(D$5>=5,D$5<5+Supuestos!$F$22),Supuestos!$F$19*Supuestos!$F$20*Supuestos!$F$21/Supuestos!$F$22,0) -> 0 | E17: =IF(AND(E$5>=5,E$5<5+Supuestos!$F$22),Supuestos!$F$19*Supuestos!$F$20*Supuestos!$F$21/Supuestos!$F$22,0) -> 0 | F17: =IF(AND(F$5>=5,F$5<5+Supuestos!$F$22),Supuestos!$F$19*Supuestos!$F$20*Supuestos!$F$21/Supuestos!$F$22,0) -> 0 | G17: =IF(AND(G$5>=5,G$5<5+Supuestos!$F$22),Supuestos!$F$19*Supuestos!$F$20*Supuestos!$F$21/Supuestos!$F$22,0) -> 60750 | H17: =IF(AND(H$5>=5,H$5<5+Supuestos!$F$22),Supuestos!$F$19*Supuestos!$F$20*Supuestos!$F$21/Supuestos!$F$22,0) -> 60750 | I17: =IF(AND(I$5>=5,I$5<5+Supuestos!$F$22),Supuestos!$F$19*Supuestos!$F$20*Supuestos!$F$21/Supuestos!$F$22,0) -> 60750 | J17: =IF(AND(J$5>=5,J$5<5+Supuestos!$F$22),Supuestos!$F$19*Supuestos!$F$20*Supuestos!$F$21/Supuestos!$F$22,0) -> 60750 | ... N17: =IF(AND(N$5>=5,N$5<5+Supuestos!$F$22),Supuestos!$F$19*Supuestos!$F$20*Supuestos!$F$21/Supuestos!$F$22,0) -> 60750 | O17: =SUM(C17:N17) -> 486000
A18: Total de ingresos | C18: =SUM(C7:C17) -> 624925 | D18: =SUM(D7:D17) -> 753175 | E18: =SUM(E7:E17) -> 743050 | F18: =SUM(F7:F17) -> 767800 | G18: =SUM(G7:G17) -> 858300 | H18: =SUM(H7:H17) -> 765300 | I18: =SUM(I7:I17) -> 765300 | J18: =SUM(J7:J17) -> 781050 | ... O18: =SUM(O7:O17) -> 9226850
A20: EGRESOS
A21: Egreso mensual base | B21: Supuestos | C21: =Supuestos!$F$23 -> 390000 | D21: =Supuestos!$F$23 -> 390000 | E21: =Supuestos!$F$23 -> 390000 | F21: =Supuestos!$F$23 -> 390000 | G21: =Supuestos!$F$23 -> 390000 | H21: =Supuestos!$F$23 -> 390000 | I21: =Supuestos!$F$23 -> 390000 | J21: =Supuestos!$F$23 -> 390000 | ... N21: =Supuestos!$F$23 -> 390000 | O21: =SUM(C21:N21) -> 4680000
A22: Gastos extraordinarios (capture aquí) | B22: Graduación, aguinaldos, impuestos… | C22: 0 | D22: 0 | E22: 0 | F22: 0 | G22: 0 | H22: 0 | I22: 0 | J22: 0 | K22: 0 | L22: 0 | M22: 0 | N22: 0 | O22: =SUM(C22:N22) -> 0
A23: Total de egresos | C23: =C21+C22 -> 390000 | D23: =D21+D22 -> 390000 | E23: =E21+E22 -> 390000 | F23: =F21+F22 -> 390000 | G23: =G21+G22 -> 390000 | H23: =H21+H22 -> 390000 | I23: =I21+I22 -> 390000 | J23: =J21+J22 -> 390000 | ... O23: =O21+O22 -> 4680000
A25: Flujo del mes | C25: =C18-C23 -> 234925 | D25: =D18-D23 -> 363175 | E25: =E18-E23 -> 353050 | F25: =F18-F23 -> 377800 | G25: =G18-G23 -> 468300 | H25: =H18-H23 -> 375300 | I25: =I18-I23 -> 375300 | J25: =J18-J23 -> 391050 | ... O25: =O18-O23 -> 4546850
A26: Flujo acumulado | C26: =C25 -> 234925 | D26: =C26+D25 -> 598100 | E26: =D26+E25 -> 951150 | F26: =E26+F25 -> 1328950 | G26: =F26+G25 -> 1797250 | H26: =G26+H25 -> 2172550 | I26: =H26+I25 -> 2547850 | J26: =I26+J25 -> 2938900 | K26: =J26+K25 -> 3314200 | ... N26: =M26+N25 -> 4546850
A27: Saldo proyectado | B27: Saldo inicial + acumulado | C27: =Supuestos!$F$24+C26 -> 234925 | D27: =Supuestos!$F$24+D26 -> 598100 | E27: =Supuestos!$F$24+E26 -> 951150 | F27: =Supuestos!$F$24+F26 -> 1328950 | G27: =Supuestos!$F$24+G26 -> 1797250 | H27: =Supuestos!$F$24+H26 -> 2172550 | I27: =Supuestos!$F$24+I26 -> 2547850 | J27: =Supuestos!$F$24+J26 -> 2938900 | ... N27: =Supuestos!$F$24+N26 -> 4546850
A28: Meses de operación que cubre el saldo | B28: Saldo ÷ egresos del mes | C28: =IFERROR(C27/C23,0) -> 0.60237179 | D28: =IFERROR(D27/D23,0) -> 1.5335897 | E28: =IFERROR(E27/E23,0) -> 2.4388462 | F28: =IFERROR(F27/F23,0) -> 3.4075641 | G28: =IFERROR(G27/G23,0) -> 4.6083333 | H28: =IFERROR(H27/H23,0) -> 5.570641 | I28: =IFERROR(I27/I23,0) -> 6.5329487 | J28: =IFERROR(J27/J23,0) -> 7.535641 | ... N28: =IFERROR(N27/N23,0) -> 11.65859

Sheet Comparativo
A1: Los tres escenarios a 12 meses
A2: Se calcula aparte de la hoja Proyección (que muestra solo el escenario en uso) y se comprueba contra ella.
A4: Concepto | B4: Pesimista | C4: Base | D4: Optimista
A5: Colegiaturas de alumnos actuales | B5: =12*Supuestos!$C$7 -> 6720000 | C5: =12*Supuestos!$D$7 -> 7200000 | D5: =12*Supuestos!$E$7 -> 7560000
A6: Licenciatura 26-3 | B6: =12*Supuestos!$C$8*Supuestos!$C$9 -> 177600 | C6: =12*Supuestos!$D$8*Supuestos!$D$9 -> 177600 | D6: =12*Supuestos!$E$8*Supuestos!$E$9 -> 177600
A7: Maestría en Educación 26-4 (inscripción, 11 colegiaturas y 3 reinscripciones) | B7: =Supuestos!$C$10*(Supuestos!$C$12+11*Supuestos!$C$11+3*Supuestos!$C$13) -> 985500 | C7: =Supuestos!$D$10*(Supuestos!$D$12+11*Supuestos!$D$11+3*Supuestos!$D$13) -> 1478250 | D7: =Supuestos!$E$10*(Supuestos!$E$12+11*Supuestos!$E$11+3*Supuestos!$E$13) -> 1971000
A8: Egresados que dejan de pagar (8 meses) | B8: =-8*Supuestos!$C$14*Supuestos!$C$15 -> -2052000 | C8: =-8*Supuestos!$D$14*Supuestos!$D$15 -> -1584000 | D8: =-8*Supuestos!$E$14*Supuestos!$E$15 -> -1224000
A9: Posgrados 27-1 (inscripción, 8 colegiaturas y 1 reinscripción) | B9: =Supuestos!$C$16*(Supuestos!$C$12+8*Supuestos!$C$17+Supuestos!$C$13) -> 992000 | C9: =Supuestos!$D$16*(Supuestos!$D$12+8*Supuestos!$D$17+Supuestos!$D$13) -> 1364000 | D9: =Supuestos!$E$16*(Supuestos!$E$12+8*Supuestos!$E$17+Supuestos!$E$13) -> 1736000
A10: Reinscripción de alumnos que continúan | B10: =2*Supuestos!$C$18*Supuestos!$C$13 -> 105000 | C10: =2*Supuestos!$D$18*Supuestos!$D$13 -> 105000 | D10: =2*Supuestos!$E$18*Supuestos!$E$13 -> 105000
A11: Titulación | B11: =Supuestos!$C$19*Supuestos!$C$20*Supuestos!$C$21*MIN(1,8/Supuestos!$C$22) -> 303750 | C11: =Supuestos!$D$19*Supuestos!$D$20*Supuestos!$D$21*MIN(1,8/Supuestos!$D$22) -> 486000 | D11: =Supuestos!$E$19*Supuestos!$E$20*Supuestos!$E$21*MIN(1,8/Supuestos!$E$22) -> 668250
A12: Total de ingresos | B12: =SUM(B5:B11) -> 7231850 | C12: =SUM(C5:C11) -> 9226850 | D12: =SUM(D5:D11) -> 10993850
A13: Total de egresos (sin extraordinarios) | B13: =12*Supuestos!$C$23 -> 5148000 | C13: =12*Supuestos!$D$23 -> 4680000 | D13: =12*Supuestos!$E$23 -> 4440000
A14: Flujo acumulado a 12 meses | B14: =B12-B13 -> 2083850 | C14: =C12-C13 -> 4546850 | D14: =D12-D13 -> 6553850
A15: Margen | B15: =IFERROR(B14/B12,0) -> 0.28814895 | C15: =IFERROR(C14/C12,0) -> 0.49278464 | D15: =IFERROR(D14/D12,0) -> 0.59613784
A17: Comprobación: ingresos del escenario en uso (Comparativo − Proyección, debe dar 0) | B17: =INDEX(B12:D12,1,Supuestos!$B$4)-Proyección!O18 -> 0
A19: Cuánto vale cada alumno en 12 meses
A20: Uno más de Maestría en Educación 26-4 | B20: =Supuestos!$D$12+11*Supuestos!$D$11+3*Supuestos!$D$13 -> 32850
A21: Uno más de posgrado 27-1 | B21: =Supuestos!$D$12+8*Supuestos!$D$17+Supuestos!$D$13 -> 12400
A22: Un egresado menos que deja de pagar | B22: =8*Supuestos!$D$15 -> 14400
